src/__init__.py
src/csvHelper.py
src/excelHelper.py
src/jsonHelper.py
src/requestHelper.py
mati1daTools-0.0.1.dist-info/LICENSE
mati1daTools-0.0.1.dist-info/METADATA
mati1daTools-0.0.1.dist-info/WHEEL
mati1daTools-0.0.1.dist-info/top_level.txt
mati1daTools-0.0.1.dist-info/RECORD
